cuecut.py
cuecut-1.0.3.dist-info/METADATA
cuecut-1.0.3.dist-info/RECORD
cuecut-1.0.3.dist-info/WHEEL
cuecut-1.0.3.dist-info/entry_points.txt
cuecut-1.0.3.dist-info/top_level.txt
