Metadata-Version: 2.1
Name: cuecut
Version: 1.0.3
Summary: Cut a CD image file by its cue file
Home-page: https://github.com/jsjyhzy/cuecut
Author: Hu Zheyang
Author-email: i@huzheyang.com
License: MIT
Platform: UNKNOWN
Classifier: Development Status :: 4 - Beta
Classifier: Intended Audience :: End Users/Desktop
Classifier: License :: OSI Approved :: MIT License
Classifier: Programming Language :: Python :: 3 :: Only
Classifier: Topic :: Multimedia :: Sound/Audio
Requires-Python: >=3
Requires-Dist: CueParser (==1.0.0)
Requires-Dist: chardet (>=3.0.0)
